{"coord":{"lon":9.1895,"lat":45.4643},"weather":[{"id":800,"main":"Clear","description":"clear sky","icon":"01d"}],"base":"stations","main":{"temp":294.09,"feels_like":293.49,"temp_min":292.97,"temp_max":295.45,"pressure":1021,"humidity":48,"sea_level":1021,"grnd_level":1007},"visibility":10000,"wind":{"speed":2.06,"deg":130},"clouds":{"all":0},"dt":1775306352,"sys":{"type":2,"id":2108619,"country":"IT","sunrise":1775278693,"sunset":1775325239},"timezone":7200,"id":3173435,"name":"Milan","cod":200}
