{"coord":{"lon":9.1895,"lat":45.4643},"weather":[{"id":500,"main":"Rain","description":"light rain","icon":"10n"}],"base":"stations","main":{"temp":283.76,"feels_like":283.02,"temp_min":281.56,"temp_max":284.27,"pressure":1019,"humidity":82,"sea_level":1019,"grnd_level":1004},"visibility":10000,"wind":{"speed":2.57,"deg":140},"rain":{"1h":0.15},"clouds":{"all":0},"dt":1740766539,"sys":{"type":2,"id":2012644,"country":"IT","sunrise":1740722615,"sunset":1740762499},"timezone":3600,"id":3173435,"name":"Milan","cod":200}
