{"coord":{"lon":9.1895,"lat":45.4643},"weather":[{"id":803,"main":"Clouds","description":"broken clouds","icon":"04d"}],"base":"stations","main":{"temp":284.42,"feels_like":283.87,"temp_min":283.52,"temp_max":285.36,"pressure":1000,"humidity":87,"sea_level":1000,"grnd_level":985},"visibility":10000,"wind":{"speed":2.24,"deg":98,"gust":2.24},"clouds":{"all":75},"dt":1741781700,"sys":{"type":2,"id":2012644,"country":"IT","sunrise":1741758095,"sunset":1741800273},"timezone":3600,"id":3173435,"name":"Milan","cod":200}
