{"coord":{"lon":9.1895,"lat":45.4643},"weather":[{"id":803,"main":"Clouds","description":"broken clouds","icon":"04d"}],"base":"stations","main":{"temp":286.84,"feels_like":286.3,"temp_min":285.97,"temp_max":287.96,"pressure":996,"humidity":78,"sea_level":996,"grnd_level":982},"visibility":10000,"wind":{"speed":4.12,"deg":120},"clouds":{"all":75},"dt":1741868523,"sys":{"type":2,"id":2012644,"country":"IT","sunrise":1741844382,"sunset":1741886752},"timezone":3600,"id":3173435,"name":"Milan","cod":200}
