{"coord":{"lon":9.1895,"lat":45.4643},"weather":[{"id":803,"main":"Clouds","description":"broken clouds","icon":"04n"}],"base":"stations","main":{"temp":290.97,"feels_like":289.62,"temp_min":289.79,"temp_max":291.73,"pressure":1012,"humidity":31,"sea_level":1012,"grnd_level":997},"visibility":10000,"wind":{"speed":4.47,"deg":288,"gust":9.83},"clouds":{"all":60},"dt":1726251373,"sys":{"type":2,"id":2012644,"country":"IT","sunrise":1726203578,"sunset":1726249128},"timezone":7200,"id":3173435,"name":"Milan","cod":200}
