{"coord":{"lon":9.1895,"lat":45.4643},"weather":[{"id":802,"main":"Clouds","description":"scattered clouds","icon":"03n"}],"base":"stations","main":{"temp":291.29,"feels_like":291.2,"temp_min":289.47,"temp_max":291.97,"pressure":1013,"humidity":78,"sea_level":1013,"grnd_level":999},"visibility":10000,"wind":{"speed":1.54,"deg":50},"clouds":{"all":40},"dt":1727288200,"sys":{"type":1,"id":6742,"country":"IT","sunrise":1727241251,"sunset":1727284526},"timezone":7200,"id":3173435,"name":"Milan","cod":200}
