{"coord":{"lon":9.1895,"lat":45.4643},"weather":[{"id":804,"main":"Clouds","description":"overcast clouds","icon":"04n"}],"base":"stations","main":{"temp":297.37,"feels_like":297.86,"temp_min":294.87,"temp_max":298.23,"pressure":1012,"humidity":77,"sea_level":1012,"grnd_level":997},"visibility":10000,"wind":{"speed":2.13,"deg":73,"gust":6.58},"clouds":{"all":91},"dt":1662574369,"sys":{"type":2,"id":2019808,"country":"IT","sunrise":1662526308,"sunset":1662573076},"timezone":7200,"id":3173435,"name":"Milan","cod":200}
