{"coord":{"lon":9.1895,"lat":45.4643},"weather":[{"id":803,"main":"Clouds","description":"broken clouds","icon":"04d"}],"base":"stations","main":{"temp":301.71,"feels_like":302.59,"temp_min":299.4,"temp_max":302.85,"pressure":1011,"humidity":53,"sea_level":1011,"grnd_level":997},"visibility":10000,"wind":{"speed":1.44,"deg":253,"gust":2.14},"clouds":{"all":78},"dt":1720981342,"sys":{"type":2,"id":2012644,"country":"IT","sunrise":1720928900,"sunset":1720984171},"timezone":7200,"id":3173435,"name":"Milan","cod":200}
