{"coord":{"lon":9.1895,"lat":45.4643},"weather":[{"id":803,"main":"Clouds","description":"broken clouds","icon":"04d"}],"base":"stations","main":{"temp":293.07,"feels_like":293.57,"temp_min":292.56,"temp_max":293.16,"pressure":1006,"humidity":94,"sea_level":1006,"grnd_level":990},"visibility":8000,"wind":{"speed":5.66,"deg":10},"clouds":{"all":75},"dt":1751825938,"sys":{"type":2,"id":20368,"country":"IT","sunrise":1751773297,"sunset":1751829241},"timezone":7200,"id":3173435,"name":"Milan","cod":200}
