{"coord":{"lon":9.1895,"lat":45.4643},"weather":[{"id":804,"main":"Clouds","description":"overcast clouds","icon":"04d"}],"base":"stations","main":{"temp":283.06,"feels_like":282.19,"temp_min":282.28,"temp_max":284.47,"pressure":1005,"humidity":85,"sea_level":1005,"grnd_level":990},"visibility":8000,"wind":{"speed":2.06,"deg":160},"clouds":{"all":100},"dt":1770728406,"sys":{"type":2,"id":2107179,"country":"IT","sunrise":1770705175,"sunset":1770741730},"timezone":3600,"id":3173435,"name":"Milan","cod":200}
