{"coord":{"lon":9.1895,"lat":45.4643},"weather":[{"id":803,"main":"Clouds","description":"broken clouds","icon":"04d"}],"base":"stations","main":{"temp":288.29,"feels_like":288.31,"temp_min":287.12,"temp_max":288.97,"pressure":1023,"humidity":94,"sea_level":1023,"grnd_level":1008},"visibility":4000,"wind":{"speed":2.06,"deg":360},"clouds":{"all":75},"dt":1729405020,"sys":{"type":2,"id":2012644,"country":"IT","sunrise":1729403177,"sunset":1729441761},"timezone":7200,"id":3173435,"name":"Milan","cod":200}
